optns/profilelike.py
optns/sampler.py
optns-0.1.0.dist-info/METADATA
optns-0.1.0.dist-info/WHEEL
optns-0.1.0.dist-info/top_level.txt
optns-0.1.0.dist-info/RECORD
