Metadata-Version: 2.2
Name: optns
Version: 0.1.0
Summary: Optimized Nested Sampling: fast inference for non-linear additive models
Requires-Python: >=3.8
Requires-Dist: numpy
Requires-Dist: scipy
Requires-Dist: scikit-learn
Requires-Dist: tqdm
Requires-Dist: ultranest
Requires-Dist: corner
Requires-Dist: matplotlib
